g4fpro/__init__.py
g4fpro/async_chat.py
g4fpro/async_image_generator.py
g4fpro/base_chat.py
g4fpro/base_image_generator.py
g4fpro/chat.py
g4fpro/exceptions.py
g4fpro/image_generator.py
g4fpro/messages.py
g4fpro/models.py
g4fpro-0.1.2.dist-info/METADATA
g4fpro-0.1.2.dist-info/WHEEL
g4fpro-0.1.2.dist-info/top_level.txt
g4fpro-0.1.2.dist-info/RECORD
