Metadata-Version: 2.4
Name: g4fpro
Version: 0.1.2
Summary: Неофициальный Python-клиент для gpt4free.pro (текст, изображения, async/sync интерфейсы)
Author: Umar
License: Proprietary
Project-URL: Homepage, https://github.com/Umar151515/g4fpro
Project-URL: Repository, https://github.com/Umar151515/g4fpro
Platform: any
Requires-Python: >=3.8
Requires-Dist: anyio==4.11.0
Requires-Dist: certifi==2025.10.5
Requires-Dist: h11==0.16.0
Requires-Dist: httpcore==1.0.9
Requires-Dist: httpx==0.28.1
Requires-Dist: idna==3.11
Requires-Dist: pillow==12.0.0
Requires-Dist: sniffio==1.3.1
